csc_cyb600_lab1_wilcox-1.0.1.data/scripts/show-current-time
csc_cyb600_lab1_wilcox-1.0.1.data/scripts/show-current-time.py
wilcox_lab_1/__init__.py
wilcox_lab_1/main.py
csc_cyb600_lab1_wilcox-1.0.1.dist-info/LICENSE
csc_cyb600_lab1_wilcox-1.0.1.dist-info/METADATA
csc_cyb600_lab1_wilcox-1.0.1.dist-info/WHEEL
csc_cyb600_lab1_wilcox-1.0.1.dist-info/top_level.txt
csc_cyb600_lab1_wilcox-1.0.1.dist-info/RECORD
