Metadata-Version: 2.1
Name: csc-cyb600-lab1-wilcox
Version: 1.0.1
Author: Gregory Wilcox
Author-email: wilcox12@canisius.edu
License: Apache License Version 2.0
License-File: LICENSE
Requires-Dist: Flask
Requires-Dist: dash
Requires-Dist: dash-bootstrap-components
